{
    "Алиссиновый синий": "#F0F8FF",
    "Античный белый": "#FAEBD7",
    "Аква": "#00FFFF",
    "Аквамарин": "#7FFFD4",
    "Лазурный": "#F0FFFF",
    "Бежевый": "#F5F5DC",
    "Бисквитный": "#FFE4C4",
    "Чёрный": "#000000",
    "Бледный миндаль": "#FFEBCD",
    "Синий": "#0000FF",
    "Сине-фиолетовый": "#8A2BE2",
    "Коричневый": "#A52A2A",
    "Коричневое дерево": "#DEB887",
    "Кадетский синий": "#5F9EA0",
    "Шартрез": "#7FFF00",
    "Шоколадный": "#D2691E",
    "Коралловый": "#FF7F50",
    "Васильковый синий": "#6495ED",
    "Кукурузный шёлк": "#FFF8DC",
    "Малиновый": "#DC143C",
    "Циан": "#00FFFF",
    "Тёмно-синий": "#00008B",
    "Тёмно-циан": "#008B8B",
    "Тёмный золотой": "#B8860B",
    "Тёмно-серый": "#A9A9A9",
    "Тёмно-зелёный": "#006400",
    "Тёмный хаки": "#BDB76B",
    "Тёмная фуксия": "#8B008B",
    "Тёмно-оливковый зелёный": "#556B2F",
    "Тёмно-оранжевый": "#FF8C00",
    "Тёмная орхидея": "#9932CC",
    "Тёмно-красный": "#8B0000",
    "Тёмный лосось": "#E9967A",
    "Тёмно-морской зелёный": "#8FBC8F",
    "Тёмный серо-синий": "#483D8B",
    "Тёмный серый сланец": "#2F4F4F",
    "Тёмный бирюзовый": "#00CED1",
    "Тёмный фиолетовый": "#9400D3",
    "Глубокий розовый": "#FF1493",
    "Глубокий небесный синий": "#00BFFF",
    "Тускло-серый": "#696969",
    "Доджер-синий": "#1E90FF",
    "Огненно-красный": "#B22222",
    "Цветочный белый": "#FFFAF0",
    "Лесной зелёный": "#228B22",
    "Фуксия": "#FF00FF",
    "Гейнсборо": "#DCDCDC",
    "Призрачный белый": "#F8F8FF",
    "Золотой": "#FFD700",
    "Золотистый стержень": "#DAA520",
    "Серый": "#808080",
    "Зелёный": "#008000",
    "Жёлто-зелёный": "#ADFF2F",
    "Медвяная роса": "#F0FFF0",
    "Ярко-розовый": "#FF69B4",
    "Индийский красный": "#CD5C5C",
    "Индиго": "#4B0082",
    "Слоновая кость": "#FFFFF0",
    "Хаки": "#F0E68C",
    "Лаванда": "#E6E6FA",
    "Лаванда румяная": "#FFF0F5",
    "Лаймовый зелёный": "#7CFC00",
    "Лимонный шифон": "#FFFACD",
    "Светло-синий": "#ADD8E6",
    "Светло-коралловый": "#F08080",
    "Светло-циан": "#E0FFFF",
    "Светло-золотисто-жёлтый": "#FAFAD2",
    "Светло-серый": "#D3D3D3",
    "Светло-зелёный": "#90EE90",
    "Светло-розовый": "#FFB6C1",
    "Светло-лососевый": "#FFA07A",
    "Светло-морской зелёный": "#20B2AA",
    "Светло-небесный синий": "#87CEFA",
    "Светлый серо-синий": "#778899",
    "Светло-стальной синий": "#B0C4DE",
    "Светло-жёлтый": "#FFFFE0",
    "Лайм": "#00FF00",
    "Лаймовый зелёный": "#32CD32",
    "Лён": "#FAF0E6",
    "Пурпурный": "#FF00FF",
    "Бордовый": "#800000",
    "Средний аквамариновый": "#66CDAA",
    "Средне-синий": "#0000CD",
    "Средняя орхидея": "#BA55D3",
    "Средний пурпурный": "#9370DB",
    "Средний морской зелёный": "#3CB371",
    "Средний серо-синий": "#7B68EE",
    "Средний весенний зелёный": "#00FA9A",
    "Средний бирюзовый": "#48D1CC",
    "Средний малиновый": "#C71585",
    "Полуночный синий": "#191970",
    "Мятный крем": "#F5FFFA",
    "Розовый туман": "#FFE4E1",
    "Мокасин": "#FFE4B5",
    "Навахо белый": "#FFDEAD",
    "Темно-синий": "#000080",
    "Старая кружева": "#FDF5E6",
    "Оливковый": "#808000",
    "Оливково-зелёный": "#6B8E23",
    "Оранжевый": "#FFA500",
    "Оранжево-красный": "#FF4500",
    "Орхидея": "#DA70D6",
    "Бледный золотой стержень": "#EEE8AA",
    "Бледно-зелёный": "#98FB98",
    "Бледный бирюзовый": "#AFEEEE",
    "Бледно-розовый": "#DB7093",
    "Папайя крем": "#FFEFD5",
    "Персиковый": "#FFDAB9",
    "Перу": "#CD853F",
    "Розовый": "#FFC0CB",
    "Слива": "#DDA0DD",
    "Пудровый синий": "#B0E0E6",
    "Фиолетовый": "#800080",
    "Ребекка пурпурный": "#663399",
    "Красный": "#FF0000",
    "Розовато-коричневый": "#BC8F8F",
    "Королевский синий": "#4169E1",
    "Коричневый седло": "#8B4513",
    "Лососевый": "#FA8072",
    "Песчаный коричневый": "#F4A460",
    "Морской зелёный": "#2E8B57",
    "Морская раковина": "#FFF5EE",
    "Сиенна": "#A0522D",
    "Серебристый": "#C0C0C0",
    "Небесно-голубой": "#87CEEB",
    "Серо-синий": "#6A5ACD",
    "Серо-голубой сланец": "#708090",
    "Снег": "#FFFAFA",
    "Весенний зелёный": "#00FF7F",
    "Стальной синий": "#4682B4",
    "Коричневый загар": "#D2B48C",
    "Бирюза": "#008080",
    "Чертополох": "#D8BFD8",
    "Томат": "#FF6347",
    "Бирюзовый": "#40E0D0",
    "Фиолетово-лиловый": "#EE82EE",
    "Пшеница": "#F5DEB3",
    "Белый": "#FFFFFF",
    "Белый дым": "#F5F5F5",
    "Жёлтый": "#FFFF00",
    "Жёлто-зелёный": "#9ACD32"
}